pydena/__init__.py
pydena/api/__init__.py
pydena/exceptions/__init__.py
pydena/models/__init__.py
pydena/models/account/__init__.py
pydena/models/blockchain/__init__.py
pydena/models/dna/__init__.py
pydena-1.1.1.dist-info/METADATA
pydena-1.1.1.dist-info/WHEEL
pydena-1.1.1.dist-info/top_level.txt
pydena-1.1.1.dist-info/zip-safe
pydena-1.1.1.dist-info/RECORD
